<q6>
	<department deptno="d001">
		<history from="1986-01-16" to="1987-03-28">1</history>
		<history from="1987-03-28" to="1987-07-25">2</history>
		<history from="1987-07-25" to="1988-03-30">3</history>
		<history from="1988-03-30" to="1988-04-25">4</history>
		<history from="1988-04-25" to="1988-09-24">5</history>
		<history from="1988-09-24" to="1989-08-24">6</history>
		<history from="1989-08-24" to="1990-01-17">7</history>
		<history from="1990-01-17" to="1991-03-14">8</history>
		<history from="1991-03-14" to="1991-06-24">9</history>
		<history from="1991-06-24" to="1992-04-27">10</history>
		<history from="1992-04-27" to="1992-12-22">11</history>
		<history from="1992-12-22" to="1993-08-03">12</history>
		<history from="1993-08-03" to="1995-02-05">13</history>
		<history from="1995-02-05" to="1995-05-24">14</history>
		<history from="1995-05-24" to="1995-07-22">13</history>
		<history from="1995-07-22" to="1996-05-04">12</history>
		<history from="1996-05-04" to="1996-07-31">13</history>
		<history from="1996-07-31" to="1996-10-04">14</history>
		<history from="1996-10-04" to="1999-01-06">15</history>
		<history from="1999-01-06" to="1999-03-20">14</history>
		<history from="1999-03-20" to="1999-05-15">15</history>
		<history from="1999-05-15" to="2001-10-20">14</history>
		<history from="2001-10-20" to="9999-12-31">13</history>
	</department>
	<department deptno="d002">
		<history from="1985-10-14" to="1987-12-18">1</history>
		<history from="1987-12-18" to="1988-05-17">2</history>
		<history from="1988-05-17" to="1988-05-18">3</history>
		<history from="1988-05-18" to="1988-05-23">4</history>
		<history from="1988-05-23" to="1988-06-12">5</history>
		<history from="1988-06-12" to="1988-06-28">6</history>
		<history from="1988-06-28" to="1989-03-24">7</history>
		<history from="1989-03-24" to="1989-06-03">8</history>
		<history from="1989-06-03" to="1990-09-07">7</history>
		<history from="1990-09-07" to="1990-12-25">6</history>
		<history from="1990-12-25" to="1991-06-01">7</history>
		<history from="1991-06-01" to="1991-06-26">8</history>
		<history from="1991-06-26" to="1991-09-13">9</history>
		<history from="1991-09-13" to="1991-11-23">10</history>
		<history from="1991-11-23" to="1992-03-21">11</history>
		<history from="1992-03-21" to="1993-02-06">12</history>
		<history from="1993-02-06" to="1993-03-21">13</history>
		<history from="1993-03-21" to="1993-08-10">14</history>
		<history from="1993-08-10" to="1994-03-17">13</history>
		<history from="1994-03-17" to="1994-07-01">12</history>
		<history from="1994-07-01" to="1994-09-28">13</history>
		<history from="1994-09-28" to="1995-05-01">14</history>
		<history from="1995-05-01" to="1995-06-19">15</history>
		<history from="1995-06-19" to="1995-08-29">16</history>
		<history from="1995-08-29" to="1996-12-21">17</history>
		<history from="1996-12-21" to="1996-12-25">18</history>
		<history from="1996-12-25" to="1997-02-14">19</history>
		<history from="1997-02-14" to="1997-06-18">20</history>
		<history from="1997-06-18" to="1997-06-28">21</history>
		<history from="1997-06-28" to="1997-08-16">22</history>
		<history from="1997-08-16" to="1997-09-16">21</history>
		<history from="1997-09-16" to="1997-10-23">22</history>
		<history from="1997-10-23" to="1999-01-26">23</history>
		<history from="1999-01-26" to="1999-01-31">22</history>
		<history from="1999-01-31" to="1999-03-03">23</history>
		<history from="1999-03-03" to="2000-01-06">24</history>
		<history from="2000-01-06" to="2000-08-10">25</history>
		<history from="2000-08-10" to="2001-06-15">24</history>
		<history from="2001-06-15" to="2002-01-01">23</history>
		<history from="2002-01-01" to="9999-12-31">22</history>
	</department>
	<department deptno="d003">
		<history from="1985-10-14" to="1985-10-20">1</history>
		<history from="1985-10-20" to="1986-08-22">2</history>
		<history from="1986-08-22" to="1987-09-21">3</history>
		<history from="1987-09-21" to="1988-01-19">4</history>
		<history from="1988-01-19" to="1988-01-30">5</history>
		<history from="1988-01-30" to="1989-09-12">6</history>
		<history from="1989-09-12" to="1990-09-20">7</history>
		<history from="1990-09-20" to="1990-11-02">8</history>
		<history from="1990-11-02" to="1991-05-21">9</history>
		<history from="1991-05-21" to="1991-12-27">10</history>
		<history from="1991-12-27" to="1992-02-02">11</history>
		<history from="1992-02-02" to="1992-02-19">12</history>
		<history from="1992-02-19" to="1992-04-28">13</history>
		<history from="1992-04-28" to="1992-05-22">14</history>
		<history from="1992-05-22" to="1992-06-04">15</history>
		<history from="1992-06-04" to="1993-08-10">16</history>
		<history from="1993-08-10" to="1994-04-29">15</history>
		<history from="1994-04-29" to="1994-09-28">16</history>
		<history from="1994-09-28" to="1994-12-23">17</history>
		<history from="1994-12-23" to="1995-01-27">18</history>
		<history from="1995-01-27" to="1995-07-29">19</history>
		<history from="1995-07-29" to="1995-08-05">20</history>
		<history from="1995-08-05" to="1996-09-04">21</history>
		<history from="1996-09-04" to="1996-12-20">22</history>
		<history from="1996-12-20" to="1997-06-28">23</history>
		<history from="1997-06-28" to="1997-07-16">24</history>
		<history from="1997-07-16" to="1999-03-03">23</history>
		<history from="1999-03-03" to="1999-03-20">24</history>
		<history from="1999-03-20" to="1999-05-17">25</history>
		<history from="1999-05-17" to="1999-11-01">26</history>
		<history from="1999-11-01" to="2001-06-11">25</history>
		<history from="2001-06-11" to="2001-10-20">24</history>
		<history from="2001-10-20" to="2002-01-01">23</history>
		<history from="2002-01-01" to="9999-12-31">22</history>
	</department>
	<department deptno="d004">
		<history from="1985-02-15" to="1985-05-13">1</history>
		<history from="1985-05-13" to="1985-07-30">2</history>
		<history from="1985-07-30" to="1985-09-11">3</history>
		<history from="1985-09-11" to="1985-11-14">4</history>
		<history from="1985-11-14" to="1985-12-15">5</history>
		<history from="1985-12-15" to="1986-01-02">6</history>
		<history from="1986-01-02" to="1986-01-20">7</history>
		<history from="1986-01-20" to="1986-05-12">8</history>
		<history from="1986-05-12" to="1986-05-28">9</history>
		<history from="1986-05-28" to="1986-06-08">10</history>
		<history from="1986-06-08" to="1986-06-23">11</history>
		<history from="1986-06-23" to="1986-08-28">12</history>
		<history from="1986-08-28" to="1986-10-30">13</history>
		<history from="1986-10-30" to="1986-12-01">14</history>
		<history from="1986-12-01" to="1986-12-17">15</history>
		<history from="1986-12-17" to="1987-02-21">16</history>
		<history from="1987-02-21" to="1987-03-31">17</history>
		<history from="1987-03-31" to="1987-04-03">18</history>
		<history from="1987-04-03" to="1987-04-29">19</history>
		<history from="1987-04-29" to="1987-06-01">20</history>
		<history from="1987-06-01" to="1987-06-04">21</history>
		<history from="1987-06-04" to="1987-08-27">22</history>
		<history from="1987-08-27" to="1987-12-12">23</history>
		<history from="1987-12-12" to="1988-01-09">24</history>
		<history from="1988-01-09" to="1988-01-18">25</history>
		<history from="1988-01-18" to="1988-03-12">26</history>
		<history from="1988-03-12" to="1988-06-08">27</history>
		<history from="1988-06-08" to="1988-06-13">28</history>
		<history from="1988-06-13" to="1988-06-21">29</history>
		<history from="1988-06-21" to="1988-07-12">30</history>
		<history from="1988-07-12" to="1988-07-24">31</history>
		<history from="1988-07-24" to="1988-09-05">32</history>
		<history from="1988-09-05" to="1988-10-20">33</history>
		<history from="1988-10-20" to="1989-02-06">34</history>
		<history from="1989-02-06" to="1989-03-31">33</history>
		<history from="1989-03-31" to="1989-04-08">34</history>
		<history from="1989-04-08" to="1989-06-23">35</history>
		<history from="1989-06-23" to="1989-09-19">36</history>
		<history from="1989-09-19" to="1989-09-24">37</history>
		<history from="1989-09-24" to="1989-10-03">38</history>
		<history from="1989-10-03" to="1989-11-28">39</history>
		<history from="1989-11-28" to="1989-11-30">40</history>
		<history from="1989-11-30" to="1990-01-04">41</history>
		<history from="1990-01-04" to="1990-01-05">42</history>
		<history from="1990-01-05" to="1990-01-19">43</history>
		<history from="1990-01-19" to="1990-02-05">44</history>
		<history from="1990-02-05" to="1990-05-25">45</history>
		<history from="1990-05-25" to="1990-06-20">46</history>
		<history from="1990-06-20" to="1990-08-17">47</history>
		<history from="1990-08-17" to="1990-10-19">46</history>
		<history from="1990-10-19" to="1990-10-24">47</history>
		<history from="1990-10-24" to="1990-11-08">48</history>
		<history from="1990-11-08" to="1990-12-08">49</history>
		<history from="1990-12-08" to="1991-02-01">50</history>
		<history from="1991-02-01" to="1991-05-11">51</history>
		<history from="1991-05-11" to="1991-05-17">52</history>
		<history from="1991-05-17" to="1991-06-06">53</history>
		<history from="1991-06-06" to="1991-06-09">54</history>
		<history from="1991-06-09" to="1991-06-19">55</history>
		<history from="1991-06-19" to="1991-09-05">56</history>
		<history from="1991-09-05" to="1991-09-18">57</history>
		<history from="1991-09-18" to="1991-10-27">58</history>
		<history from="1991-10-27" to="1991-11-21">59</history>
		<history from="1991-11-21" to="1991-12-04">60</history>
		<history from="1991-12-04" to="1991-12-18">61</history>
		<history from="1991-12-18" to="1992-01-22">62</history>
		<history from="1992-01-22" to="1992-03-01">63</history>
		<history from="1992-03-01" to="1992-03-19">64</history>
		<history from="1992-03-19" to="1992-04-04">65</history>
		<history from="1992-04-04" to="1992-05-13">66</history>
		<history from="1992-05-13" to="1992-06-14">67</history>
		<history from="1992-06-14" to="1992-08-14">68</history>
		<history from="1992-08-14" to="1992-10-15">70</history>
		<history from="1992-10-15" to="1992-12-11">71</history>
		<history from="1992-12-11" to="1992-12-12">70</history>
		<history from="1992-12-12" to="1992-12-20">71</history>
		<history from="1992-12-20" to="1993-01-15">72</history>
		<history from="1993-01-15" to="1993-02-01">73</history>
		<history from="1993-02-01" to="1993-02-12">74</history>
		<history from="1993-02-12" to="1993-05-12">73</history>
		<history from="1993-05-12" to="1993-05-21">74</history>
		<history from="1993-05-21" to="1993-06-16">75</history>
		<history from="1993-06-16" to="1993-07-24">76</history>
		<history from="1993-07-24" to="1993-08-05">77</history>
		<history from="1993-08-05" to="1993-08-23">76</history>
		<history from="1993-08-23" to="1993-12-09">77</history>
		<history from="1993-12-09" to="1994-01-05">78</history>
		<history from="1994-01-05" to="1994-02-17">77</history>
		<history from="1994-02-17" to="1994-03-09">79</history>
		<history from="1994-03-09" to="1994-04-09">80</history>
		<history from="1994-04-09" to="1994-05-21">81</history>
		<history from="1994-05-21" to="1994-08-29">82</history>
		<history from="1994-08-29" to="1994-12-30">83</history>
		<history from="1994-12-30" to="1995-01-02">82</history>
		<history from="1995-01-02" to="1995-01-03">83</history>
		<history from="1995-01-03" to="1995-03-20">84</history>
		<history from="1995-03-20" to="1995-04-06">85</history>
		<history from="1995-04-06" to="1995-04-26">86</history>
		<history from="1995-04-26" to="1995-05-07">87</history>
		<history from="1995-05-07" to="1995-06-27">88</history>
		<history from="1995-06-27" to="1995-10-22">89</history>
		<history from="1995-10-22" to="1995-12-03">90</history>
		<history from="1995-12-03" to="1995-12-15">91</history>
		<history from="1995-12-15" to="1996-03-25">92</history>
		<history from="1996-03-25" to="1996-05-02">93</history>
		<history from="1996-05-02" to="1996-05-16">94</history>
		<history from="1996-05-16" to="1996-07-06">95</history>
		<history from="1996-07-06" to="1996-08-05">96</history>
		<history from="1996-08-05" to="1996-08-24">97</history>
		<history from="1996-08-24" to="1996-11-16">98</history>
		<history from="1996-11-16" to="1996-11-24">99</history>
		<history from="1996-11-24" to="1997-01-31">100</history>
		<history from="1997-01-31" to="1997-03-07">101</history>
		<history from="1997-03-07" to="1997-04-26">100</history>
		<history from="1997-04-26" to="1997-07-16">101</history>
		<history from="1997-07-16" to="1997-09-23">102</history>
		<history from="1997-09-23" to="1997-10-30">103</history>
		<history from="1997-10-30" to="1997-12-30">102</history>
		<history from="1997-12-30" to="1998-01-16">103</history>
		<history from="1998-01-16" to="1998-01-23">102</history>
		<history from="1998-01-23" to="1998-04-25">101</history>
		<history from="1998-04-25" to="1998-05-27">102</history>
		<history from="1998-05-27" to="1998-06-14">103</history>
		<history from="1998-06-14" to="1998-07-01">104</history>
		<history from="1998-07-01" to="1998-07-05">105</history>
		<history from="1998-07-05" to="1998-09-14">106</history>
		<history from="1998-09-14" to="1998-11-11">107</history>
		<history from="1998-11-11" to="1999-01-23">106</history>
		<history from="1999-01-23" to="1999-01-24">107</history>
		<history from="1999-01-24" to="1999-04-19">108</history>
		<history from="1999-04-19" to="1999-04-27">109</history>
		<history from="1999-04-27" to="1999-07-06">110</history>
		<history from="1999-07-06" to="1999-09-17">111</history>
		<history from="1999-09-17" to="1999-10-16">112</history>
		<history from="1999-10-16" to="1999-11-14">113</history>
		<history from="1999-11-14" to="1999-12-06">112</history>
		<history from="1999-12-06" to="2000-10-04">111</history>
		<history from="2000-10-04" to="2000-10-27">110</history>
		<history from="2000-10-27" to="2000-11-15">109</history>
		<history from="2000-11-15" to="2001-04-14">108</history>
		<history from="2001-04-14" to="2001-07-26">107</history>
		<history from="2001-07-26" to="2002-05-06">106</history>
		<history from="2002-05-06" to="2002-06-22">105</history>
		<history from="2002-06-22" to="9999-12-31">104</history>
	</department>
	<department deptno="d005">
		<history from="1985-02-24" to="1985-05-17">1</history>
		<history from="1985-05-17" to="1985-06-05">2</history>
		<history from="1985-06-05" to="1985-07-06">3</history>
		<history from="1985-07-06" to="1985-08-02">4</history>
		<history from="1985-08-02" to="1985-08-31">5</history>
		<history from="1985-08-31" to="1985-10-14">6</history>
		<history from="1985-10-14" to="1986-01-11">7</history>
		<history from="1986-01-11" to="1986-02-26">8</history>
		<history from="1986-02-26" to="1986-03-14">9</history>
		<history from="1986-03-14" to="1986-04-10">10</history>
		<history from="1986-04-10" to="1986-05-23">11</history>
		<history from="1986-05-23" to="1986-06-26">12</history>
		<history from="1986-06-26" to="1986-10-19">13</history>
		<history from="1986-10-19" to="1986-11-16">14</history>
		<history from="1986-11-16" to="1986-12-17">15</history>
		<history from="1986-12-17" to="1987-01-27">16</history>
		<history from="1987-01-27" to="1987-03-23">15</history>
		<history from="1987-03-23" to="1987-04-03">16</history>
		<history from="1987-04-03" to="1987-07-25">17</history>
		<history from="1987-07-25" to="1987-08-17">18</history>
		<history from="1987-08-17" to="1987-08-28">19</history>
		<history from="1987-08-28" to="1987-09-08">20</history>
		<history from="1987-09-08" to="1987-09-18">21</history>
		<history from="1987-09-18" to="1987-11-04">22</history>
		<history from="1987-11-04" to="1987-12-12">23</history>
		<history from="1987-12-12" to="1988-02-10">24</history>
		<history from="1988-02-10" to="1988-04-19">25</history>
		<history from="1988-04-19" to="1988-04-29">26</history>
		<history from="1988-04-29" to="1988-05-17">27</history>
		<history from="1988-05-17" to="1988-05-25">28</history>
		<history from="1988-05-25" to="1988-06-22">29</history>
		<history from="1988-06-22" to="1988-08-28">30</history>
		<history from="1988-08-28" to="1988-09-23">31</history>
		<history from="1988-09-23" to="1988-09-30">32</history>
		<history from="1988-09-30" to="1988-10-31">33</history>
		<history from="1988-10-31" to="1989-05-03">34</history>
		<history from="1989-05-03" to="1989-05-21">35</history>
		<history from="1989-05-21" to="1989-08-01">36</history>
		<history from="1989-08-01" to="1989-08-07">37</history>
		<history from="1989-08-07" to="1989-09-10">38</history>
		<history from="1989-09-10" to="1989-10-06">39</history>
		<history from="1989-10-06" to="1990-01-29">38</history>
		<history from="1990-01-29" to="1990-02-01">39</history>
		<history from="1990-02-01" to="1990-05-30">40</history>
		<history from="1990-05-30" to="1990-08-05">41</history>
		<history from="1990-08-05" to="1990-08-13">42</history>
		<history from="1990-08-13" to="1990-08-17">43</history>
		<history from="1990-08-17" to="1990-09-02">42</history>
		<history from="1990-09-02" to="1990-10-20">43</history>
		<history from="1990-10-20" to="1990-12-05">44</history>
		<history from="1990-12-05" to="1991-02-19">45</history>
		<history from="1991-02-19" to="1991-03-14">46</history>
		<history from="1991-03-14" to="1991-05-17">47</history>
		<history from="1991-05-17" to="1991-08-25">48</history>
		<history from="1991-08-25" to="1991-08-30">47</history>
		<history from="1991-08-30" to="1991-09-01">48</history>
		<history from="1991-09-01" to="1991-09-18">49</history>
		<history from="1991-09-18" to="1991-10-06">50</history>
		<history from="1991-10-06" to="1991-10-22">51</history>
		<history from="1991-10-22" to="1991-11-22">52</history>
		<history from="1991-11-22" to="1991-12-08">53</history>
		<history from="1991-12-08" to="1992-01-15">54</history>
		<history from="1992-01-15" to="1992-02-02">55</history>
		<history from="1992-02-02" to="1992-06-02">56</history>
		<history from="1992-06-02" to="1992-06-09">55</history>
		<history from="1992-06-09" to="1992-09-13">56</history>
		<history from="1992-09-13" to="1992-10-11">57</history>
		<history from="1992-10-11" to="1992-11-10">58</history>
		<history from="1992-11-10" to="1992-11-18">59</history>
		<history from="1992-11-18" to="1992-12-18">60</history>
		<history from="1992-12-18" to="1992-12-28">61</history>
		<history from="1992-12-28" to="1993-01-16">62</history>
		<history from="1993-01-16" to="1993-01-28">63</history>
		<history from="1993-01-28" to="1993-02-14">64</history>
		<history from="1993-02-14" to="1993-03-12">65</history>
		<history from="1993-03-12" to="1993-03-31">66</history>
		<history from="1993-03-31" to="1993-05-01">67</history>
		<history from="1993-05-01" to="1993-05-22">68</history>
		<history from="1993-05-22" to="1993-06-29">67</history>
		<history from="1993-06-29" to="1993-07-02">66</history>
		<history from="1993-07-02" to="1993-10-25">67</history>
		<history from="1993-10-25" to="1993-10-28">68</history>
		<history from="1993-10-28" to="1993-11-08">69</history>
		<history from="1993-11-08" to="1993-12-29">70</history>
		<history from="1993-12-29" to="1994-02-27">71</history>
		<history from="1994-02-27" to="1994-06-28">72</history>
		<history from="1994-06-28" to="1994-07-09">73</history>
		<history from="1994-07-09" to="1994-09-29">74</history>
		<history from="1994-09-29" to="1994-11-01">75</history>
		<history from="1994-11-01" to="1994-12-02">76</history>
		<history from="1994-12-02" to="1995-03-31">75</history>
		<history from="1995-03-31" to="1995-04-02">76</history>
		<history from="1995-04-02" to="1995-11-12">77</history>
		<history from="1995-11-12" to="1995-12-13">78</history>
		<history from="1995-12-13" to="1996-01-16">79</history>
		<history from="1996-01-16" to="1996-01-21">80</history>
		<history from="1996-01-21" to="1996-01-28">81</history>
		<history from="1996-01-28" to="1996-02-26">82</history>
		<history from="1996-02-26" to="1996-04-22">83</history>
		<history from="1996-04-22" to="1996-06-08">84</history>
		<history from="1996-06-08" to="1996-07-15">85</history>
		<history from="1996-07-15" to="1996-09-02">87</history>
		<history from="1996-09-02" to="1996-09-11">88</history>
		<history from="1996-09-11" to="1996-09-21">89</history>
		<history from="1996-09-21" to="1996-12-16">90</history>
		<history from="1996-12-16" to="1996-12-25">91</history>
		<history from="1996-12-25" to="1997-02-02">92</history>
		<history from="1997-02-02" to="1997-02-14">93</history>
		<history from="1997-02-14" to="1997-04-04">92</history>
		<history from="1997-04-04" to="1997-04-26">93</history>
		<history from="1997-04-26" to="1997-05-02">94</history>
		<history from="1997-05-02" to="1997-05-26">95</history>
		<history from="1997-05-26" to="1997-07-16">96</history>
		<history from="1997-07-16" to="1997-08-15">97</history>
		<history from="1997-08-15" to="1997-08-24">98</history>
		<history from="1997-08-24" to="1997-09-26">99</history>
		<history from="1997-09-26" to="1997-10-15">100</history>
		<history from="1997-10-15" to="1997-12-10">99</history>
		<history from="1997-12-10" to="1998-01-12">100</history>
		<history from="1998-01-12" to="1998-02-04">101</history>
		<history from="1998-02-04" to="1998-03-11">102</history>
		<history from="1998-03-11" to="1998-03-15">103</history>
		<history from="1998-03-15" to="1998-04-01">104</history>
		<history from="1998-04-01" to="1998-04-06">105</history>
		<history from="1998-04-06" to="1998-05-24">104</history>
		<history from="1998-05-24" to="1998-06-28">105</history>
		<history from="1998-06-28" to="1998-07-17">106</history>
		<history from="1998-07-17" to="1998-07-20">107</history>
		<history from="1998-07-20" to="1998-08-06">108</history>
		<history from="1998-08-06" to="1998-08-10">109</history>
		<history from="1998-08-10" to="1998-11-01">110</history>
		<history from="1998-11-01" to="1998-11-04">109</history>
		<history from="1998-11-04" to="1998-12-16">110</history>
		<history from="1998-12-16" to="1998-12-18">111</history>
		<history from="1998-12-18" to="1999-01-30">112</history>
		<history from="1999-01-30" to="1999-02-23">113</history>
		<history from="1999-02-23" to="1999-03-08">112</history>
		<history from="1999-03-08" to="1999-05-04">111</history>
		<history from="1999-05-04" to="1999-05-07">110</history>
		<history from="1999-05-07" to="1999-05-13">109</history>
		<history from="1999-05-13" to="1999-06-30">110</history>
		<history from="1999-06-30" to="1999-07-19">111</history>
		<history from="1999-07-19" to="1999-09-03">112</history>
		<history from="1999-09-03" to="1999-09-16">113</history>
		<history from="1999-09-16" to="1999-09-27">114</history>
		<history from="1999-09-27" to="1999-11-03">115</history>
		<history from="1999-11-03" to="2000-01-08">116</history>
		<history from="2000-01-08" to="2000-01-25">117</history>
		<history from="2000-01-25" to="2000-02-04">118</history>
		<history from="2000-02-04" to="2000-07-31">117</history>
		<history from="2000-07-31" to="2001-01-15">116</history>
		<history from="2001-01-15" to="2001-04-15">115</history>
		<history from="2001-04-15" to="2001-08-13">114</history>
		<history from="2001-08-13" to="2001-10-11">113</history>
		<history from="2001-10-11" to="2002-01-31">112</history>
		<history from="2002-01-31" to="2002-07-06">111</history>
		<history from="2002-07-06" to="2002-07-15">110</history>
		<history from="2002-07-15" to="9999-12-31">109</history>
	</department>
	<department deptno="d006">
		<history from="1985-02-18" to="1985-09-11">1</history>
		<history from="1985-09-11" to="1986-01-27">2</history>
		<history from="1986-01-27" to="1987-01-02">3</history>
		<history from="1987-01-02" to="1987-03-04">4</history>
		<history from="1987-03-04" to="1987-03-18">5</history>
		<history from="1987-03-18" to="1987-08-03">6</history>
		<history from="1987-08-03" to="1987-10-08">5</history>
		<history from="1987-10-08" to="1988-06-13">6</history>
		<history from="1988-06-13" to="1988-12-19">7</history>
		<history from="1988-12-19" to="1988-12-29">8</history>
		<history from="1988-12-29" to="1989-05-17">9</history>
		<history from="1989-05-17" to="1990-11-18">10</history>
		<history from="1990-11-18" to="1990-12-18">11</history>
		<history from="1990-12-18" to="1991-01-02">12</history>
		<history from="1991-01-02" to="1991-09-05">11</history>
		<history from="1991-09-05" to="1991-09-18">12</history>
		<history from="1991-09-18" to="1992-03-01">13</history>
		<history from="1992-03-01" to="1992-03-03">14</history>
		<history from="1992-03-03" to="1992-08-30">15</history>
		<history from="1992-08-30" to="1992-11-26">16</history>
		<history from="1992-11-26" to="1993-02-12">17</history>
		<history from="1993-02-12" to="1993-03-24">16</history>
		<history from="1993-03-24" to="1993-05-14">15</history>
		<history from="1993-05-14" to="1993-11-10">16</history>
		<history from="1993-11-10" to="1994-02-17">17</history>
		<history from="1994-02-17" to="1994-04-04">18</history>
		<history from="1994-04-04" to="1994-12-03">19</history>
		<history from="1994-12-03" to="1995-01-03">20</history>
		<history from="1995-01-03" to="1996-01-26">21</history>
		<history from="1996-01-26" to="1996-02-20">22</history>
		<history from="1996-02-20" to="1996-04-12">23</history>
		<history from="1996-04-12" to="1996-06-12">24</history>
		<history from="1996-06-12" to="1996-11-24">25</history>
		<history from="1996-11-24" to="1997-09-12">26</history>
		<history from="1997-09-12" to="1997-10-03">27</history>
		<history from="1997-10-03" to="1998-02-02">28</history>
		<history from="1998-02-02" to="1998-02-22">29</history>
		<history from="1998-02-22" to="1998-09-26">28</history>
		<history from="1998-09-26" to="1998-10-06">29</history>
		<history from="1998-10-06" to="1999-04-19">30</history>
		<history from="1999-04-19" to="1999-10-16">31</history>
		<history from="1999-10-16" to="1999-10-23">32</history>
		<history from="1999-10-23" to="1999-10-25">33</history>
		<history from="1999-10-25" to="2000-06-30">34</history>
		<history from="2000-06-30" to="2000-11-15">33</history>
		<history from="2000-11-15" to="2000-12-05">32</history>
		<history from="2000-12-05" to="2001-04-25">31</history>
		<history from="2001-04-25" to="9999-12-31">30</history>
	</department>
	<department deptno="d007">
		<history from="1985-02-21" to="1985-03-19">1</history>
		<history from="1985-03-19" to="1985-06-16">2</history>
		<history from="1985-06-16" to="1985-10-12">3</history>
		<history from="1985-10-12" to="1985-11-06">4</history>
		<history from="1985-11-06" to="1986-01-16">5</history>
		<history from="1986-01-16" to="1986-03-01">6</history>
		<history from="1986-03-01" to="1986-06-07">7</history>
		<history from="1986-06-07" to="1986-07-22">8</history>
		<history from="1986-07-22" to="1986-10-23">9</history>
		<history from="1986-10-23" to="1986-10-29">10</history>
		<history from="1986-10-29" to="1987-03-28">11</history>
		<history from="1987-03-28" to="1987-03-30">12</history>
		<history from="1987-03-30" to="1987-08-03">13</history>
		<history from="1987-08-03" to="1987-08-07">14</history>
		<history from="1987-08-07" to="1987-10-08">15</history>
		<history from="1987-10-08" to="1988-02-29">16</history>
		<history from="1988-02-29" to="1988-06-13">17</history>
		<history from="1988-06-13" to="1988-09-02">18</history>
		<history from="1988-09-02" to="1988-10-18">19</history>
		<history from="1988-10-18" to="1988-11-03">20</history>
		<history from="1988-11-03" to="1989-01-10">21</history>
		<history from="1989-01-10" to="1989-04-16">22</history>
		<history from="1989-04-16" to="1989-05-28">23</history>
		<history from="1989-05-28" to="1989-06-05">24</history>
		<history from="1989-06-05" to="1989-08-11">25</history>
		<history from="1989-08-11" to="1989-09-02">26</history>
		<history from="1989-09-02" to="1989-09-16">27</history>
		<history from="1989-09-16" to="1989-11-12">28</history>
		<history from="1989-11-12" to="1989-12-02">29</history>
		<history from="1989-12-02" to="1990-01-10">30</history>
		<history from="1990-01-10" to="1990-06-14">31</history>
		<history from="1990-06-14" to="1990-10-12">32</history>
		<history from="1990-10-12" to="1990-10-26">33</history>
		<history from="1990-10-26" to="1990-11-19">34</history>
		<history from="1990-11-19" to="1990-12-25">35</history>
		<history from="1990-12-25" to="1991-05-28">36</history>
		<history from="1991-05-28" to="1991-08-13">37</history>
		<history from="1991-08-13" to="1991-09-13">38</history>
		<history from="1991-09-13" to="1991-09-26">39</history>
		<history from="1991-09-26" to="1991-11-23">40</history>
		<history from="1991-11-23" to="1992-01-17">42</history>
		<history from="1992-01-17" to="1992-02-12">43</history>
		<history from="1992-02-12" to="1992-03-12">44</history>
		<history from="1992-03-12" to="1992-04-06">45</history>
		<history from="1992-04-06" to="1992-04-18">46</history>
		<history from="1992-04-18" to="1992-06-04">47</history>
		<history from="1992-06-04" to="1992-08-31">48</history>
		<history from="1992-08-31" to="1992-11-16">49</history>
		<history from="1992-11-16" to="1992-11-22">50</history>
		<history from="1992-11-22" to="1992-12-12">51</history>
		<history from="1992-12-12" to="1992-12-22">52</history>
		<history from="1992-12-22" to="1992-12-29">53</history>
		<history from="1992-12-29" to="1993-09-06">54</history>
		<history from="1993-09-06" to="1993-10-08">55</history>
		<history from="1993-10-08" to="1993-10-16">56</history>
		<history from="1993-10-16" to="1993-10-17">57</history>
		<history from="1993-10-17" to="1993-12-06">58</history>
		<history from="1993-12-06" to="1993-12-08">59</history>
		<history from="1993-12-08" to="1994-01-28">60</history>
		<history from="1994-01-28" to="1994-02-17">61</history>
		<history from="1994-02-17" to="1994-03-10">62</history>
		<history from="1994-03-10" to="1994-03-20">63</history>
		<history from="1994-03-20" to="1994-03-21">62</history>
		<history from="1994-03-21" to="1994-05-29">63</history>
		<history from="1994-05-29" to="1994-06-18">64</history>
		<history from="1994-06-18" to="1994-07-05">65</history>
		<history from="1994-07-05" to="1994-09-05">66</history>
		<history from="1994-09-05" to="1994-10-03">67</history>
		<history from="1994-10-03" to="1994-10-23">68</history>
		<history from="1994-10-23" to="1994-11-13">69</history>
		<history from="1994-11-13" to="1995-02-19">70</history>
		<history from="1995-02-19" to="1995-04-12">71</history>
		<history from="1995-04-12" to="1995-07-24">72</history>
		<history from="1995-07-24" to="1996-01-22">73</history>
		<history from="1996-01-22" to="1996-01-26">74</history>
		<history from="1996-01-26" to="1996-01-29">75</history>
		<history from="1996-01-29" to="1996-03-25">76</history>
		<history from="1996-03-25" to="1996-03-29">75</history>
		<history from="1996-03-29" to="1996-04-20">74</history>
		<history from="1996-04-20" to="1996-07-15">73</history>
		<history from="1996-07-15" to="1996-07-21">74</history>
		<history from="1996-07-21" to="1996-07-31">73</history>
		<history from="1996-07-31" to="1996-08-03">74</history>
		<history from="1996-08-03" to="1996-08-27">75</history>
		<history from="1996-08-27" to="1996-08-30">74</history>
		<history from="1996-08-30" to="1997-05-08">75</history>
		<history from="1997-05-08" to="1997-06-08">76</history>
		<history from="1997-06-08" to="1998-02-07">77</history>
		<history from="1998-02-07" to="1998-02-11">78</history>
		<history from="1998-02-11" to="1998-10-07">79</history>
		<history from="1998-10-07" to="1998-10-14">80</history>
		<history from="1998-10-14" to="1998-10-29">81</history>
		<history from="1998-10-29" to="1999-03-30">82</history>
		<history from="1999-03-30" to="1999-05-28">83</history>
		<history from="1999-05-28" to="1999-06-27">84</history>
		<history from="1999-06-27" to="1999-08-06">85</history>
		<history from="1999-08-06" to="1999-08-14">84</history>
		<history from="1999-08-14" to="1999-09-20">83</history>
		<history from="1999-09-20" to="1999-10-30">82</history>
		<history from="1999-10-30" to="1999-10-31">83</history>
		<history from="1999-10-31" to="1999-11-09">82</history>
		<history from="1999-11-09" to="1999-12-01">81</history>
		<history from="1999-12-01" to="2000-01-26">82</history>
		<history from="2000-01-26" to="2000-02-21">83</history>
		<history from="2000-02-21" to="2000-09-23">82</history>
		<history from="2000-09-23" to="2001-01-09">81</history>
		<history from="2001-01-09" to="2001-03-13">80</history>
		<history from="2001-03-13" to="2001-06-15">79</history>
		<history from="2001-06-15" to="2001-12-23">78</history>
		<history from="2001-12-23" to="2002-01-02">77</history>
		<history from="2002-01-02" to="2002-05-08">76</history>
		<history from="2002-05-08" to="9999-12-31">75</history>
	</department>
	<department deptno="d008">
		<history from="1985-06-05" to="1985-10-14">1</history>
		<history from="1985-10-14" to="1985-11-20">2</history>
		<history from="1985-11-20" to="1986-12-06">3</history>
		<history from="1986-12-06" to="1987-04-16">4</history>
		<history from="1987-04-16" to="1987-04-18">5</history>
		<history from="1987-04-18" to="1987-09-18">6</history>
		<history from="1987-09-18" to="1987-09-20">7</history>
		<history from="1987-09-20" to="1987-10-22">8</history>
		<history from="1987-10-22" to="1987-10-30">9</history>
		<history from="1987-10-30" to="1988-01-17">10</history>
		<history from="1988-01-17" to="1989-02-10">11</history>
		<history from="1989-02-10" to="1989-04-06">12</history>
		<history from="1989-04-06" to="1990-01-03">13</history>
		<history from="1990-01-03" to="1990-01-05">14</history>
		<history from="1990-01-05" to="1990-01-15">15</history>
		<history from="1990-01-15" to="1990-09-02">14</history>
		<history from="1990-09-02" to="1990-09-15">15</history>
		<history from="1990-09-15" to="1991-12-08">16</history>
		<history from="1991-12-08" to="1992-03-02">17</history>
		<history from="1992-03-02" to="1992-04-04">16</history>
		<history from="1992-04-04" to="1992-04-25">15</history>
		<history from="1992-04-25" to="1992-06-20">16</history>
		<history from="1992-06-20" to="1992-06-25">17</history>
		<history from="1992-06-25" to="1992-07-17">18</history>
		<history from="1992-07-17" to="1992-09-19">19</history>
		<history from="1992-09-19" to="1992-12-28">20</history>
		<history from="1992-12-28" to="1993-02-14">21</history>
		<history from="1993-02-14" to="1993-05-22">22</history>
		<history from="1993-05-22" to="1993-08-22">21</history>
		<history from="1993-08-22" to="1994-02-27">20</history>
		<history from="1994-02-27" to="1994-04-21">21</history>
		<history from="1994-04-21" to="1994-07-09">22</history>
		<history from="1994-07-09" to="1994-10-10">23</history>
		<history from="1994-10-10" to="1995-02-20">24</history>
		<history from="1995-02-20" to="1995-03-31">23</history>
		<history from="1995-03-31" to="1995-05-25">24</history>
		<history from="1995-05-25" to="1995-06-26">25</history>
		<history from="1995-06-26" to="1996-06-16">26</history>
		<history from="1996-06-16" to="1996-09-27">27</history>
		<history from="1996-09-27" to="1997-01-31">28</history>
		<history from="1997-01-31" to="1997-04-04">29</history>
		<history from="1997-04-04" to="1997-11-08">30</history>
		<history from="1997-11-08" to="1998-02-04">29</history>
		<history from="1998-02-04" to="1998-02-20">30</history>
		<history from="1998-02-20" to="1998-07-23">31</history>
		<history from="1998-07-23" to="1998-09-02">32</history>
		<history from="1998-09-02" to="1998-11-01">33</history>
		<history from="1998-11-01" to="1999-01-24">32</history>
		<history from="1999-01-24" to="1999-04-27">33</history>
		<history from="1999-04-27" to="1999-04-30">34</history>
		<history from="1999-04-30" to="1999-05-27">35</history>
		<history from="1999-05-27" to="2000-07-09">36</history>
		<history from="2000-07-09" to="2002-07-06">35</history>
		<history from="2002-07-06" to="9999-12-31">34</history>
	</department>
	<department deptno="d009">
		<history from="1985-02-18" to="1985-04-02">1</history>
		<history from="1985-04-02" to="1985-05-13">2</history>
		<history from="1985-05-13" to="1985-09-08">3</history>
		<history from="1985-09-08" to="1987-07-25">4</history>
		<history from="1987-07-25" to="1988-03-03">5</history>
		<history from="1988-03-03" to="1988-06-06">6</history>
		<history from="1988-06-06" to="1988-09-02">7</history>
		<history from="1988-09-02" to="1989-05-28">8</history>
		<history from="1989-05-28" to="1989-09-20">9</history>
		<history from="1989-09-20" to="1990-01-22">10</history>
		<history from="1990-01-22" to="1990-04-07">11</history>
		<history from="1990-04-07" to="1990-08-13">12</history>
		<history from="1990-08-13" to="1990-10-19">13</history>
		<history from="1990-10-19" to="1991-09-28">14</history>
		<history from="1991-09-28" to="1991-11-21">15</history>
		<history from="1991-11-21" to="1992-04-06">16</history>
		<history from="1992-04-06" to="1992-05-04">17</history>
		<history from="1992-05-04" to="1992-05-24">18</history>
		<history from="1992-05-24" to="1992-06-09">17</history>
		<history from="1992-06-09" to="1992-12-11">18</history>
		<history from="1992-12-11" to="1993-03-31">17</history>
		<history from="1993-03-31" to="1993-12-08">18</history>
		<history from="1993-12-08" to="1994-01-07">19</history>
		<history from="1994-01-07" to="1994-10-06">20</history>
		<history from="1994-10-06" to="1994-12-11">21</history>
		<history from="1994-12-11" to="1994-12-22">22</history>
		<history from="1994-12-22" to="1994-12-24">23</history>
		<history from="1994-12-24" to="1995-04-26">24</history>
		<history from="1995-04-26" to="1995-12-14">25</history>
		<history from="1995-12-14" to="1996-02-24">26</history>
		<history from="1996-02-24" to="1996-03-29">27</history>
		<history from="1996-03-29" to="1996-08-11">26</history>
		<history from="1996-08-11" to="1996-10-23">27</history>
		<history from="1996-10-23" to="1996-11-09">28</history>
		<history from="1996-11-09" to="1997-08-22">27</history>
		<history from="1997-08-22" to="1997-12-26">28</history>
		<history from="1997-12-26" to="1998-02-15">29</history>
		<history from="1998-02-15" to="1998-05-01">30</history>
		<history from="1998-05-01" to="1998-07-01">31</history>
		<history from="1998-07-01" to="1998-07-05">32</history>
		<history from="1998-07-05" to="1998-09-09">33</history>
		<history from="1998-09-09" to="1999-01-06">34</history>
		<history from="1999-01-06" to="1999-01-24">33</history>
		<history from="1999-01-24" to="1999-12-29">32</history>
		<history from="1999-12-29" to="2000-08-15">33</history>
		<history from="2000-08-15" to="2000-10-27">32</history>
		<history from="2000-10-27" to="9999-12-31">31</history>
	</department>
</q6>